pipelinez/__init__.py
pipelinez/_version.py
pipelinez/api.py
pipelinez/completion_patch.py
pipelinez/constants.py
pipelinez/extract_names.py
pipelinez/macro_tracer.py
pipelinez/pipeline_tracer.py
pipelinez/placeholders.py
pipelinez/traceback_patch.py
pipelinez/utils.py
pipelinez/version.py
pipelinez-0.0.1.dist-info/licenses/docs/LICENSE.txt
pipelinez-0.0.1.dist-info/METADATA
pipelinez-0.0.1.dist-info/WHEEL
pipelinez-0.0.1.dist-info/top_level.txt
pipelinez-0.0.1.dist-info/RECORD
