Metadata-Version: 2.4
Name: pipelinez
Version: 0.0.1
Summary: Powerful pipeline syntax for IPython and Jupyter
Home-page: https://github.com/smacke/pipelinez
Author: Stephen Macke
Author-email: stephen.macke@gmail.com
License: BSD-3-Clause
Classifier: Development Status :: 3 - Alpha
Classifier: Intended Audience :: Developers
Classifier: License :: OSI Approved :: BSD License
Classifier: Natural Language :: English
Classifier: Programming Language :: Python :: 3.9
Classifier: Programming Language :: Python :: 3.10
Classifier: Programming Language :: Python :: 3.11
Classifier: Programming Language :: Python :: 3.12
Classifier: Programming Language :: Python :: 3.13
Classifier: Programming Language :: Python :: 3.14
Requires-Python: >=3.9
License-File: docs/LICENSE.txt
Requires-Dist: ipyflow-core>=0.0.221
Requires-Dist: pyccolo>=0.0.77
Provides-Extra: test
Requires-Dist: black; extra == "test"
Requires-Dist: hypothesis; extra == "test"
Requires-Dist: isort; extra == "test"
Requires-Dist: mypy; extra == "test"
Requires-Dist: pytest; extra == "test"
Requires-Dist: pytest-cov; extra == "test"
Requires-Dist: ruff; extra == "test"
Provides-Extra: dev
Requires-Dist: build; extra == "dev"
Requires-Dist: pycln; extra == "dev"
Requires-Dist: twine; extra == "dev"
Requires-Dist: versioneer; extra == "dev"
Requires-Dist: black; extra == "dev"
Requires-Dist: hypothesis; extra == "dev"
Requires-Dist: isort; extra == "dev"
Requires-Dist: mypy; extra == "dev"
Requires-Dist: pytest; extra == "dev"
Requires-Dist: pytest-cov; extra == "dev"
Requires-Dist: ruff; extra == "dev"
Dynamic: license-file
